tools/LIBzek.py
tools/LIBzx.py
tools/__init__.py
felegToo-0.0.3.dist-info/METADATA
felegToo-0.0.3.dist-info/WHEEL
felegToo-0.0.3.dist-info/top_level.txt
felegToo-0.0.3.dist-info/RECORD
