Metadata-Version: 2.1
Name: felegToo
Version: 0.0.3
Summary: cftools
Home-page: https://cubefel.netlify.app
Author: feleg
Author-email: false.fas527@gmail.com
Keywords: cfPass
Requires-Python: >=3.6
Requires-Dist: requests >=2.25.1
